{
  "lsarFormatVersion": 2,
  "lsarContents": [
    {
      "XADIndex": 0,
      "XADLastModificationDate": "2008-10-16 00:15:25 +0000",
      "StuffItFlags": 64,
      "XADFileName": "Hypercard",
      "XADFinderFlags": 768,
      "XADCreationDate": "2008-10-16 00:15:11 +0000",
      "XADIsDirectory": true
    },
    {
      "XADIndex": 1,
      "XADLastModificationDate": "2008-10-16 00:15:25 +0000",
      "StuffItFlags": 64,
      "XADFileName": "Hypercard/Help Stacks",
      "XADFinderFlags": 256,
      "XADCreationDate": "2008-10-16 00:15:11 +0000",
      "XADIsDirectory": true
    },
    {
      "XADCompressedSize": 303301,
      "XADFinderFlags": 0,
      "XADDataLength": 303301,
      "XADDataOffset": 390,
      "XADIndex": 2,
      "StuffItCRC16": 59800,
      "XADFileType": 1398030667,
      "XADFileName": "Hypercard/Help Stacks/Help",
      "StuffItFlags": 0,
      "XADCompressionName": "LZ+Huffman",
      "XADCreationDate": "1987-11-25 15:00:44 +0000",
      "XADFileCreator": 1464421444,
      "XADLastModificationDate": "1997-07-17 18:54:22 +0000",
      "StuffItCompressionMethod": 13,
      "XADFileSize": 589824
    },
    {
      "XADCompressedSize": 11549,
      "XADFinderFlags": 0,
      "XADDataLength": 11549,
      "XADDataOffset": 303785,
      "XADIndex": 3,
      "StuffItCRC16": 39644,
      "XADFileType": 1398030667,
      "XADFileName": "Hypercard/Help Stacks/Help Index",
      "StuffItFlags": 0,
      "XADCompressionName": "LZ+Huffman",
      "XADCreationDate": "1987-11-25 15:04:37 +0000",
      "XADFileCreator": 1464421444,
      "XADLastModificationDate": "1989-09-06 10:58:01 +0000",
      "StuffItCompressionMethod": 13,
      "XADFileSize": 52668
    },
    {
      "XADCompressedSize": 209273,
      "XADFinderFlags": 8448,
      "XADDataLength": 209273,
      "XADDataOffset": 315489,
      "XADIndex": 4,
      "StuffItCRC16": 48227,
      "XADFileType": 1095782476,
      "XADFileName": "Hypercard/HyperCard",
      "StuffItFlags": 0,
      "XADCompressionName": "LZ+Huffman",
      "XADCreationDate": "1989-08-28 12:13:16 +0000",
      "XADFileCreator": 1464421444,
      "XADLastModificationDate": "1989-09-20 20:33:14 +0000",
      "XADIsResourceFork": true,
      "StuffItCompressionMethod": 13,
      "XADFileSize": 393103
    },
    {
      "XADIndex": 5,
      "XADLastModificationDate": "2008-10-16 00:15:25 +0000",
      "StuffItFlags": 64,
      "XADFileName": "Hypercard/HyperCard Stacks",
      "XADFinderFlags": 256,
      "XADCreationDate": "2008-10-16 00:15:12 +0000",
      "XADIsDirectory": true
    },
    {
      "XADCompressedSize": 5177,
      "XADFinderFlags": 0,
      "XADDataLength": 5177,
      "XADDataOffset": 524953,
      "XADIndex": 6,
      "StuffItCRC16": 17627,
      "XADFileType": 1398030667,
      "XADFileName": "Hypercard/HyperCard Stacks/Address",
      "StuffItFlags": 0,
      "XADCompressionName": "LZ+Huffman",
      "XADCreationDate": "1987-11-25 15:25:03 +0000",
      "XADFileCreator": 1464421444,
      "XADLastModificationDate": "1997-01-20 15:40:25 +0000",
      "StuffItCompressionMethod": 13,
      "XADFileSize": 16384
    },
    {
      "XADCompressedSize": 597,
      "XADFinderFlags": 0,
      "XADDataLength": 597,
      "XADDataOffset": 530236,
      "XADIndex": 7,
      "StuffItCRC16": 16189,
      "XADFileType": 1398030667,
      "XADFileName": "Hypercard/HyperCard Stacks/DateBook",
      "StuffItFlags": 0,
      "XADCompressionName": "LZ+Huffman",
      "XADCreationDate": "1989-09-20 20:26:00 +0000",
      "XADFileCreator": 1464421444,
      "XADLastModificationDate": "1997-01-20 15:42:04 +0000",
      "XADIsResourceFork": true,
      "StuffItCompressionMethod": 13,
      "XADFileSize": 881
    },
    {
      "XADCompressedSize": 9981,
      "XADFinderFlags": 0,
      "XADDataLength": 9981,
      "XADDataOffset": 530833,
      "XADIndex": 8,
      "StuffItCRC16": 13151,
      "XADFileType": 1398030667,
      "XADFileName": "Hypercard/HyperCard Stacks/DateBook",
      "StuffItFlags": 0,
      "XADCompressionName": "LZ+Huffman",
      "XADCreationDate": "1989-09-20 20:26:00 +0000",
      "XADFileCreator": 1464421444,
      "XADLastModificationDate": "1997-01-20 15:42:04 +0000",
      "StuffItCompressionMethod": 13,
      "XADFileSize": 41536
    },
    {
      "XADCompressedSize": 2393,
      "XADFinderFlags": 0,
      "XADDataLength": 2393,
      "XADDataOffset": 540908,
      "XADIndex": 9,
      "StuffItCRC16": 38144,
      "XADFileType": 1398030667,
      "XADFileName": "Hypercard/HyperCard Stacks/File Index",
      "StuffItFlags": 0,
      "XADCompressionName": "LZ+Huffman",
      "XADCreationDate": "1987-11-25 15:25:22 +0000",
      "XADFileCreator": 1464421444,
      "XADLastModificationDate": "1989-09-06 10:48:06 +0000",
      "StuffItCompressionMethod": 13,
      "XADFileSize": 9088
    },
    {
      "XADCompressedSize": 6625,
      "XADFinderFlags": 0,
      "XADDataLength": 6625,
      "XADDataOffset": 543389,
      "XADIndex": 10,
      "StuffItCRC16": 8426,
      "XADFileType": 1398030667,
      "XADFileName": "Hypercard/HyperCard Stacks/Home",
      "StuffItFlags": 0,
      "XADCompressionName": "LZ+Huffman",
      "XADCreationDate": "1987-11-25 15:24:57 +0000",
      "XADFileCreator": 1464421444,
      "XADLastModificationDate": "1904-01-01 05:02:22 +0000",
      "StuffItCompressionMethod": 13,
      "XADFileSize": 19264
    },
    {
      "XADCompressedSize": 1613,
      "XADFinderFlags": 0,
      "XADDataLength": 1613,
      "XADDataOffset": 550107,
      "XADIndex": 11,
      "StuffItCRC16": 48403,
      "XADFileType": 1398030667,
      "XADFileName": "Hypercard/HyperCard Stacks/HyperCalc",
      "StuffItFlags": 0,
      "XADCompressionName": "LZ+Huffman",
      "XADCreationDate": "1987-11-25 15:26:13 +0000",
      "XADFileCreator": 1464421444,
      "XADLastModificationDate": "1989-09-06 10:48:21 +0000",
      "StuffItCompressionMethod": 13,
      "XADFileSize": 6720
    },
    {
      "XADCompressedSize": 1965,
      "XADFinderFlags": 0,
      "XADDataLength": 1965,
      "XADDataOffset": 551814,
      "XADIndex": 12,
      "StuffItCRC16": 44556,
      "XADFileType": 1398030667,
      "XADFileName": "Hypercard/HyperCard Stacks/My Address",
      "StuffItFlags": 0,
      "XADCompressionName": "LZ+Huffman",
      "XADCreationDate": "1993-05-19 16:11:14 +0000",
      "XADFileCreator": 1464421444,
      "XADLastModificationDate": "1993-05-19 16:13:10 +0000",
      "StuffItCompressionMethod": 13,
      "XADFileSize": 8192
    },
    {
      "XADCompressedSize": 4985,
      "XADFinderFlags": 0,
      "XADDataLength": 4985,
      "XADDataOffset": 553868,
      "XADIndex": 13,
      "StuffItCRC16": 21371,
      "XADFileType": 1398030667,
      "XADFileName": "Hypercard/HyperCard Stacks/Phone",
      "StuffItFlags": 0,
      "XADCompressionName": "LZ+Huffman",
      "XADCreationDate": "1987-11-25 15:26:00 +0000",
      "XADFileCreator": 1464421444,
      "XADLastModificationDate": "1999-07-16 13:38:39 +0000",
      "StuffItCompressionMethod": 13,
      "XADFileSize": 17920
    },
    {
      "XADCompressedSize": 2393,
      "XADFinderFlags": 0,
      "XADDataLength": 2393,
      "XADDataOffset": 558947,
      "XADIndex": 14,
      "StuffItCRC16": 1491,
      "XADFileType": 1398030667,
      "XADFileName": "Hypercard/HyperCard Stacks/Quotations",
      "StuffItFlags": 0,
      "XADCompressionName": "LZ+Huffman",
      "XADCreationDate": "1987-11-25 15:25:36 +0000",
      "XADFileCreator": 1464421444,
      "XADLastModificationDate": "1997-01-20 15:35:39 +0000",
      "StuffItCompressionMethod": 13,
      "XADFileSize": 7968
    },
    {
      "XADCompressedSize": 225,
      "XADFinderFlags": 0,
      "XADDataLength": 225,
      "XADDataOffset": 561465,
      "XADIndex": 15,
      "StuffItCRC16": 59966,
      "XADFileType": 1398030667,
      "XADFileName": "Hypercard/HyperCard Stacks/Version 1.2.5 Release Notes",
      "StuffItFlags": 0,
      "XADCompressionName": "LZ+Huffman",
      "XADCreationDate": "1988-04-04 14:25:03 +0000",
      "XADFileCreator": 1464421444,
      "XADLastModificationDate": "1993-05-19 16:07:34 +0000",
      "XADIsResourceFork": true,
      "StuffItCompressionMethod": 13,
      "XADFileSize": 418
    },
    {
      "XADCompressedSize": 27353,
      "XADFinderFlags": 0,
      "XADDataLength": 27353,
      "XADDataOffset": 561690,
      "XADIndex": 16,
      "StuffItCRC16": 38375,
      "XADFileType": 1398030667,
      "XADFileName": "Hypercard/HyperCard Stacks/Version 1.2.5 Release Notes",
      "StuffItFlags": 0,
      "XADCompressionName": "LZ+Huffman",
      "XADCreationDate": "1988-04-04 14:25:03 +0000",
      "XADFileCreator": 1464421444,
      "XADLastModificationDate": "1993-05-19 16:07:34 +0000",
      "StuffItCompressionMethod": 13,
      "XADFileSize": 90112
    },
    {
      "XADIndex": 17,
      "XADLastModificationDate": "2008-10-16 00:15:25 +0000",
      "StuffItFlags": 64,
      "XADFileName": "Hypercard/Idea Stacks",
      "XADFinderFlags": 256,
      "XADCreationDate": "2008-10-16 00:15:12 +0000",
      "XADIsDirectory": true
    },
    {
      "XADCompressedSize": 140465,
      "XADFinderFlags": 0,
      "XADDataLength": 140465,
      "XADDataOffset": 589279,
      "XADIndex": 18,
      "StuffItCRC16": 34417,
      "XADFileType": 1398030667,
      "XADFileName": "Hypercard/Idea Stacks/Art Ideas",
      "StuffItFlags": 0,
      "XADCompressionName": "LZ+Huffman",
      "XADCreationDate": "1987-11-25 15:51:30 +0000",
      "XADFileCreator": 1464421444,
      "XADLastModificationDate": "1989-09-06 10:58:42 +0000",
      "StuffItCompressionMethod": 13,
      "XADFileSize": 177792
    },
    {
      "XADCompressedSize": 12125,
      "XADFinderFlags": 0,
      "XADDataLength": 12125,
      "XADDataOffset": 729840,
      "XADIndex": 19,
      "StuffItCRC16": 39598,
      "XADFileType": 1398030667,
      "XADFileName": "Hypercard/Idea Stacks/Button Ideas",
      "StuffItFlags": 0,
      "XADCompressionName": "LZ+Huffman",
      "XADCreationDate": "1987-11-25 15:50:10 +0000",
      "XADFileCreator": 1464421444,
      "XADLastModificationDate": "1989-09-06 10:58:51 +0000",
      "StuffItCompressionMethod": 13,
      "XADFileSize": 38112
    },
    {
      "XADCompressedSize": 87297,
      "XADFinderFlags": 0,
      "XADDataLength": 87297,
      "XADDataOffset": 742059,
      "XADIndex": 20,
      "StuffItCRC16": 49536,
      "XADFileType": 1398030667,
      "XADFileName": "Hypercard/Idea Stacks/Card Ideas",
      "StuffItFlags": 0,
      "XADCompressionName": "LZ+Huffman",
      "XADCreationDate": "1987-11-25 15:51:43 +0000",
      "XADFileCreator": 1464421444,
      "XADLastModificationDate": "1989-09-06 10:59:06 +0000",
      "StuffItCompressionMethod": 13,
      "XADFileSize": 134656
    },
    {
      "XADCompressedSize": 218725,
      "XADFinderFlags": 0,
      "XADDataLength": 218725,
      "XADDataOffset": 829451,
      "XADIndex": 21,
      "StuffItCRC16": 37207,
      "XADFileType": 1398030667,
      "XADFileName": "Hypercard/Idea Stacks/Stack Ideas",
      "StuffItFlags": 0,
      "XADCompressionName": "LZ+Huffman",
      "XADCreationDate": "1987-11-25 15:22:35 +0000",
      "XADFileCreator": 1464421444,
      "XADLastModificationDate": "1989-09-06 10:59:38 +0000",
      "StuffItCompressionMethod": 13,
      "XADFileSize": 403008
    },
    {
      "XADIndex": 22,
      "XADLastModificationDate": "2008-10-16 00:15:25 +0000",
      "StuffItFlags": 64,
      "XADFileName": "Hypercard/More Stacks",
      "XADFinderFlags": 768,
      "XADCreationDate": "2008-10-16 00:15:12 +0000",
      "XADIsDirectory": true
    },
    {
      "XADCompressedSize": 377,
      "XADFinderFlags": 256,
      "XADDataLength": 377,
      "XADDataOffset": 1048427,
      "XADIndex": 23,
      "StuffItCRC16": 719,
      "XADFileType": 1398030667,
      "XADFileName": "Hypercard/More Stacks/Area Codes",
      "StuffItFlags": 0,
      "XADCompressionName": "LZ+Huffman",
      "XADCreationDate": "1987-11-25 15:28:06 +0000",
      "XADFileCreator": 1464421444,
      "XADLastModificationDate": "1989-09-06 10:49:19 +0000",
      "XADIsResourceFork": true,
      "StuffItCompressionMethod": 13,
      "XADFileSize": 546
    },
    {
      "XADCompressedSize": 13105,
      "XADFinderFlags": 256,
      "XADDataLength": 13105,
      "XADDataOffset": 1048804,
      "XADIndex": 24,
      "StuffItCRC16": 23921,
      "XADFileType": 1398030667,
      "XADFileName": "Hypercard/More Stacks/Area Codes",
      "StuffItFlags": 0,
      "XADCompressionName": "LZ+Huffman",
      "XADCreationDate": "1987-11-25 15:28:06 +0000",
      "XADFileCreator": 1464421444,
      "XADLastModificationDate": "1989-09-06 10:49:19 +0000",
      "StuffItCompressionMethod": 13,
      "XADFileSize": 36704
    },
    {
      "XADCompressedSize": 17773,
      "XADFinderFlags": 256,
      "XADDataLength": 17773,
      "XADDataOffset": 1062001,
      "XADIndex": 25,
      "StuffItCRC16": 48965,
      "XADFileType": 1398030667,
      "XADFileName": "Hypercard/More Stacks/Clip Art",
      "StuffItFlags": 0,
      "XADCompressionName": "LZ+Huffman",
      "XADCreationDate": "1987-11-25 15:27:00 +0000",
      "XADFileCreator": 1464421444,
      "XADLastModificationDate": "1989-09-06 10:49:29 +0000",
      "StuffItCompressionMethod": 13,
      "XADFileSize": 29408
    },
    {
      "XADCompressedSize": 1965,
      "XADFinderFlags": 256,
      "XADDataLength": 1965,
      "XADDataOffset": 1079881,
      "XADIndex": 26,
      "StuffItCRC16": 3464,
      "XADFileType": 1398030667,
      "XADFileName": "Hypercard/More Stacks/Documents",
      "StuffItFlags": 0,
      "XADCompressionName": "LZ+Huffman",
      "XADCreationDate": "1987-11-25 15:16:53 +0000",
      "XADFileCreator": 1464421444,
      "XADLastModificationDate": "1997-01-20 16:45:00 +0000",
      "XADIsResourceFork": true,
      "StuffItCompressionMethod": 13,
      "XADFileSize": 3129
    },
    {
      "XADCompressedSize": 3257,
      "XADFinderFlags": 256,
      "XADDataLength": 3257,
      "XADDataOffset": 1081846,
      "XADIndex": 27,
      "StuffItCRC16": 43465,
      "XADFileType": 1398030667,
      "XADFileName": "Hypercard/More Stacks/Documents",
      "StuffItFlags": 0,
      "XADCompressionName": "LZ+Huffman",
      "XADCreationDate": "1987-11-25 15:16:53 +0000",
      "XADFileCreator": 1464421444,
      "XADLastModificationDate": "1997-01-20 16:45:00 +0000",
      "StuffItCompressionMethod": 13,
      "XADFileSize": 9728
    },
    {
      "XADCompressedSize": 5517,
      "XADFinderFlags": 256,
      "XADDataLength": 5517,
      "XADDataOffset": 1085192,
      "XADIndex": 28,
      "StuffItCRC16": 39196,
      "XADFileType": 1398030667,
      "XADFileName": "Hypercard/More Stacks/Plots",
      "StuffItFlags": 0,
      "XADCompressionName": "LZ+Huffman",
      "XADCreationDate": "1987-11-25 15:26:45 +0000",
      "XADFileCreator": 1464421444,
      "XADLastModificationDate": "1989-09-06 10:49:53 +0000",
      "StuffItCompressionMethod": 13,
      "XADFileSize": 13792
    },
    {
      "XADCompressedSize": 53577,
      "XADFinderFlags": 256,
      "XADDataLength": 53577,
      "XADDataOffset": 1090803,
      "XADIndex": 29,
      "StuffItCRC16": 2749,
      "XADFileType": 1398030667,
      "XADFileName": "Hypercard/More Stacks/Slide Show",
      "StuffItFlags": 0,
      "XADCompressionName": "LZ+Huffman",
      "XADCreationDate": "1987-11-25 15:27:00 +0000",
      "XADFileCreator": 1464421444,
      "XADLastModificationDate": "1989-09-06 10:54:38 +0000",
      "StuffItCompressionMethod": 13,
      "XADFileSize": 63776
    }
  ],
  "lsarEncoding": "macintosh",
  "lsarConfidence": 0,
  "lsarFormatName": "StuffIt 5",
  "lsarProperties": {
    "XADVolumes": [
      "archive/HyperCard_1.2.5.sit"
    ],
    "XADArchiveName": "HyperCard_1.2.5.sit"
  }
}
